{
  "enableGossip": false,
  "userGossip": [
    "Pssst, si **{name}** ang dami na ng gastos!",
    "Buti ka pa **{name}**, parang may pabrika ka ng pera!",
    "Si **{name}** hindi ba nauubusan ng sweldo?",
    "Abot na naman ng langit ang card ni **{name}** ah.",
    "Akala ko may inflation, pero si **{name}** parang hindi ramdam.",
    "Unlimited credit card ba 'yan si **{name}**?",
    "Palamig mo nga pera mo **{name}**, baka mapaso ka!",
    "Sana all tulad ni **{name}**, walang sawang swipe!",
    "Lugi na naman wallet ni **{name}** niyan.",
    "Si **{name}** at Shopee, Lazada ata ang tunay na ka-forever.",
    "Parang Christmas araw-araw kay **{name}** ah.",
    "Si **{name}**, sweldo lang pero parang bonus na kung gumastos!",
    "Bank account ni **{name}**, may hemorrhage na yata.",
    "Si **{name}** lakwatsero na, shopaholic pa!",
    "Diyos ko, tulungan mo pa ngang i-budget ang money ni **{name}**.",
    "Ang wallet ni **{name}**, parang butas na salaan.",
    "Si **{name}** parang may buy 1 take all sa gastos ah.",
    "Anong petsa na, si **{name}** pulos utang pa rin!",
    "Sana talent ko rin yang magpadami ng resibo tulad ni **{name}**.",
    "Gusto mo ATM ni **{name}**, i-autograph ko na rin?",
    "Si **{name}** puro gastos, kailan naman 'yung ipon?",
    "Akala ko ginto na 'yang kinikikay ni **{name}**.",
    "'Teh, si **{name}** gastos goals talaga!",
    "Si **{name}** mayaman yarn o matindi lang talaga ang self-love?",
    "Si **{name}**, savings? Anong klaseng ulam 'yon?",
    "Si **{name}** swipe para sa ekonomiya daw!",
    "Si **{name}**, next time save naman!",
    "Akala ko kay **{name}**, 'Gumastos' ay apelyido niya.",
    "Pangarap ko rin yan tulad ni **{name}**, maging broke in style.",
    "Si **{name}**, sweldo mo dinadaan mo lang sa kamay.",
    "Ang bilis ng pera kay **{name}**, parang shuttle bus.",
    "Si **{name}** bili dito, bili doon, savings nasaan?",
    "Akala ni **{name}** may gold mine sa ilalim ng kama.",
    "Inggit ako sa credit card ni **{name}**, never nagpapahinga.",
    "Pera ni **{name}** ba 'yan o Monopoly money?",
    "Si **{name}** suksok dito, labas doon—pera ba 'yan o spaghetti?",
    "Workshop ng gastos, si **{name}** na ang instructor!",
    "Si **{name}** na ang CEO ng gastos corporation.",
    "Hanggang saan kaya ang limit ng credit card ni **{name}**?",
    "Minsan tanong ko, si **{name}** may pera ka bang di mo pa nagagastos?",
    "Yung si **{name}**, parang may ATM sa bulsa eh.",
    "Si **{name}** ba 'yan o si Imelda Marcos?",
    "Nakita ko si **{name}** sa mall, buong department store binili.",
    "Si **{name}** ang bagay na 'Rich Kid of Instagram' eh.",
    "Yung lifestyle ni **{name}**, akala mo heiress ng Ayala.",
    "Si **{name}** parang nag-shopping therapy araw-araw.",
    "Ano bang trabaho ni **{name}**? Money printer?",
    "Si **{name}** yung tipo na nag-Grab para sa isang block.",
    "Yung si **{name}**, mas kilala ng cashier kaysa sa nanay niya.",
    "Si **{name}** collector ng credit cards ata.",
    "Parang si **{name}** allergic sa word na 'sale'.",
    "Si **{name}** yung nag-order ng Starbucks via Grab.",
    "Yung si **{name}**, signature move: tap to pay.",
    "Si **{name}** parang may sponsorship sa mga mall.",
    "Yung wallet ni **{name}**, mas manipis pa sa papel.",
    "Si **{name}** yung nag-grocery ng branded lahat.",
    "Parang si **{name}** may personal shopper sa Zalora.",
    "Si **{name}** yung bumili ng phone case na mas mahal pa sa phone.",
    "Yung si **{name}**, nag-invest sa lahat except sa sarili.",
    "Si **{name}** parang may VIP card sa lahat ng store.",
    "Yung lifestyle ni **{name}**, parang may trust fund."
  ],
  "eventGossip": [
    "Uy, ganito pala ang buhay ng mga mayaman sa **{event}**!",
  "Ayos, glamor lang sa **{event}**, budget sa loob?",
  "Feeling VIP kayo sa **{event}**, pero sampung piso ang budget?",
  "Nagpa-party kayo sa **{event}**, pero sa wallet mali-mali.",
  "Akala namin si Mr./Ms. Extravaganza kayo sa **{event}**, eh tagal ng pila!",
  "Enjoy kayo d'yan sa **{event}**, kami dito, bossing budget pa rin!",
  "**{event}** spree? Bahala kayo, credit card niyo ang magpapadala.",
  "Para kayong artista, laging may entourage ng gastos sa **{event}**.",
  "Mamasyal kayo sa **{event}** pero anak-pawis pa rin sa sweldo.",
  "Cinema trip ba 'to o malaking excuse lang para sa **{event}**?",
  "Ang daming bestseller sa **{event}**, kayo na siguro ang bestseller ng gastos.",
  "Mukhang marathon 'to ng kartel ng gastos sa **{event}**!",
  "Happy hour sa **{event}**? Para kayong nag-happy ulan ng pera!",
  "Ang ganda ng trip niyo sa **{event}**, parang hindi niyo kilala si budget.",
  "Parang award-winning ang discount na hindi niyo sinayang sa **{event}**.",
  "Swak sa catch-up sa **{event}**, swak din sa kabado ng wallet niyo.",
  "Kumusta naman ang ekonomiya niyo pagkatapos ng **{event}**?",
  "Laging nasa spotlight kayo sa **{event}**, pero ang tagal maubos ang pera.",
  "Bili dito, bili doon sa **{event}**, mapapahiya na kayo sa cashier.",
  "Sweldo, tapos **{event}**, tapos... forever broke na kayo.",
  "Lakas maka-food trip sa **{event}**, lakas din maka-empty bank account niyo.",
  "Para kayong viral hit—madaling lumabas sa **{event}**, mabilis din mag-expire ang pera niyo.",
  "Di niyo ba iniinspect presyo sa **{event}**? Feeling tayo?",
  "So much for ‘budget-friendly’ sa **{event}** plans niyo.",
  "Ang lakas maka-“just one more” sa shopping list niyo sa **{event}**.",
  "Parang adik kayo sa sale sa **{event}**, hindi gumagaling.",
  "Sinasayang niyo ang pera sa **{event}**, nakakatuwa.",
  "Mukhang “magastos” ang middle name niyo sa **{event}**!",
  "Kung may award sa ‘wasteful’ sa **{event}**, panalo kayo!",
  "Laging may dahilan kayo para gumastos sa **{event}**, pero walang dahilan para mag-ipon."
  ],
  "snarkyEmojis": [
    "😏",
    "🙄",
    "😤",
    "🤨",
    "😒",
    "🤑"
  ],
  "userAnswers": [
    "Flex lang daw.",
    "Deserve niya daw.",
    "Bahala na raw.",
    "YOLO daw!",
    "Happy naman daw siya.",
    "Treat yourself daw!",
    "Rewards lang daw.",
    "Sweldo naman daw.",
    "Self-care daw!",
    "Mind your own daw.",
    "May pera naman daw.",
    "Laban lang daw.",
    "Minsan lang naman daw.",
    "Keri niya daw!",
    "Worth it naman daw!",
    "Akalain mo yun daw!",
    "Secret lang daw.",
    "Sakit sa ulo daw!",
    "Live life daw!",
    "Ikaw na daw!",
    "Pasiklab lang daw.",
    "Ikaw ba yan daw?",
    "Hanap buhay daw!",
    "Bigay todo daw!",
    "Wag daw selos.",
    "Level up daw!",
    "Victory dance daw!",
    "One time lang daw!",
    "Pasensya na daw.",
    "Goals daw niya!",
    "Eh di wow"
  ],
  "eventAnswers": [
    "Tama raw sila.",
    "Aba, nga daw sila!",
    "Seryoso raw sila?",
    "Walang kwenta daw sila.",
    "Char daw sila.",
    "Keri raw nila.",
    "Pabibo raw sila.",
    "Booster daw sila.",
    "Good vibes daw sila.",
    "Sakit skills daw nila.",
    "Lakas maka daw sila!",
    "Chill daw sila.",
    "Tulad daw nila.",
    "Basta saya raw sila.",
    "Walang pake daw sila.",
    "Game pa daw sila!",
    "Kapit lang daw sila.",
    "Walang forever daw sila.",
    "Kain daw sila.",
    "Papaiyak daw sila!",
    "Simsim raw nila.",
    "Must try raw nila!",
    "Effort daw nila!",
    "Trip daw nila!",
    "Basta gastos daw sila!",
    "Kanya-kanya daw sila.",
    "Todo effort daw nila.",
    "Level up daw sila!",
    "Solve na daw sila!",
    "Pasensya na daw sila.",
    "Eh di wow"
  ],
  "answerEmojis": [
    "💅",
    "🤷‍♀️",
    "😎",
    "💪",
    "🙃",
    "✨"
  ]
}